{
    "description": "Mapzen is an open, sustainable, and accessible mapping platform. Our tools let you display, search, and navigate your world.", 
    "fullname": "Mapzen", 
    "id": 404734197, 
    "key": "",
    "license": "https://github.com/whosonfirst-data/whosonfirst-data/blob/master/LICENSE.md#license", 
    "license_text": "Remember, some sources require attribution, some do not. Mapzen's original work, including the format and structure that allows Who's On First to operate, is made available under the Creative Commons Zero designation, and a shout out would be lovely.", 
    "license_type": "CC0", 
    "mz_associated": 1,
    "name": "mapzen", 
    "prefix": "mz", 
    "url": "https://www.mapzen.com/", 
    "usage_concordance": 0, 
    "usage_geometry": 1, 
    "usage_property": 1
}